addok_trigrams/__init__.py
addok_trigrams-1.1.1.dist-info/METADATA
addok_trigrams-1.1.1.dist-info/RECORD
addok_trigrams-1.1.1.dist-info/WHEEL
addok_trigrams-1.1.1.dist-info/entry_points.txt
addok_trigrams-1.1.1.dist-info/top_level.txt
