Metadata-Version: 2.1
Name: addok-trigrams
Version: 1.1.1
Summary: Trigram based algorithm for Addok.
Home-page: https://github.com/addok/addok-trigrams
Author: Yohan Boniface
Author-email: yohan.boniface@data.gouv.fr
License: WTFPL
Keywords: addok geocoding
Platform: UNKNOWN
Classifier: Development Status :: 5 - Production/Stable
Classifier: Intended Audience :: Developers
Classifier: Topic :: Scientific/Engineering :: GIS
Classifier: Programming Language :: Python :: 3
Classifier: Programming Language :: Python :: 3.4
Classifier: Programming Language :: Python :: 3.5
Classifier: Programming Language :: Python :: 3.6
Provides-Extra: test
Requires-Dist: addok
Provides-Extra: test
Requires-Dist: pytest; extra == 'test'
